.DS_Store
myLib/__init__.py
myLib/datastructures/__init__.py
myLib/datastructures/linear/CDLL.py
myLib/datastructures/linear/CSLL.py
myLib/datastructures/linear/DLL.py
myLib/datastructures/linear/QueueLL.py
myLib/datastructures/linear/SLL.py
myLib/datastructures/linear/StackLL.py
myLib/datastructures/linear/__init__.py
myLib/datastructures/nodes/DNode.py
myLib/datastructures/nodes/SNode.py
myLib/datastructures/nodes/TNode.py
myLib/datastructures/nodes/__init__.py
myLib/datastructures/trees/AVL.py
myLib/datastructures/trees/BST.py
myLib/datastructures/trees/__init__.py
ensf338grp26prj-1.15.dist-info/METADATA
ensf338grp26prj-1.15.dist-info/WHEEL
ensf338grp26prj-1.15.dist-info/top_level.txt
ensf338grp26prj-1.15.dist-info/RECORD
