Metadata-Version: 2.1
Name: ensf338grp26prj
Version: 1.15
Summary: A simple package for data structures
Author: Erik and Tony
